{
  "date": "2025-06-24",
  "count": 1,
  "posts": [
    {
      "id": "51ec9c332aa6",
      "title": "ByteDance Introduces Astra: A Dual-Model Architecture for Autonomous Robot Navigation",
      "url": "https://syncedreview.com/2025/06/24/bytedance-introduces-astra-a-dual-model-architecture-for-autonomous-robot-navigation/",
      "source": "Synced Review",
      "category": "ai_research",
      "language": "en",
      "priority": "medium",
      "published": "2025-06-24T09:17:01+00:00",
      "summary": "ByteDance introduces Astra, an innovative dual-model architecture revolutionizing robot navigation in complex indoor environments. The post ByteDance Introduces Astra: A Dual-Model Architecture for Autonomous Robot Navigation first appeared on Synced .",
      "author": "Synced",
      "tags": [
        "Research"
      ],
      "has_full_text": false
    }
  ]
}