{
  "date": "2026-02-08",
  "count": 1,
  "posts": [
    {
      "id": "c5568844fd29",
      "title": "Side Business to Startup",
      "url": "https://venturefounders.com/side-business-to-startup/",
      "source": "Venture Founders",
      "category": "startups_vc",
      "language": "en",
      "priority": "low",
      "published": "2026-02-08T22:07:44+00:00",
      "summary": "Side Business to Startup: About 45 percent of million Americans have a side business, in addition to their regular paid employment. That amounts to nearly half of American full time workers who have a side hustle. Just over ten per cent of them say they earn more than $1,000 a month from their side business. [&#8230;] The post Side Business to Startup appeared first on Venture Founders .",
      "author": "Will Keyser",
      "tags": [
        "Business Purpose: Priorities & Models",
        "Passion or Autonomy",
        "Traditional or New Legal Forms and Certifications",
        "Business Plan and Initial Funding",
        "startup",
        "entrepreneur",
        "entrepreneurship"
      ],
      "has_full_text": true
    }
  ]
}